peppy_esolang/compiler.py
peppy_esolang/main.py
peppy_esolang/vm.py
peppy_esolang-0.1.0.dist-info/entry_points.txt
peppy_esolang-0.1.0.dist-info/LICENSE
peppy_esolang-0.1.0.dist-info/METADATA
peppy_esolang-0.1.0.dist-info/WHEEL
peppy_esolang-0.1.0.dist-info/RECORD
